XSS_Checker/__init__.py
XSS_Checker-22.12.1.dist-info/LICENSE
XSS_Checker-22.12.1.dist-info/METADATA
XSS_Checker-22.12.1.dist-info/WHEEL
XSS_Checker-22.12.1.dist-info/entry_points.txt
XSS_Checker-22.12.1.dist-info/top_level.txt
XSS_Checker-22.12.1.dist-info/RECORD
