Metadata-Version: 2.1
Name: XSS-Checker
Version: 22.12.1
Summary: XSS-Checker is a tool used to Check / Validate for XSS vulnerabilities
Home-page: https://github.com/truocphan/XSS-Checker
Author: Truoc Phan
Author-email: truocphan112017@gmail.com
License: MIT
Classifier: Programming Language :: Python :: 3
License-File: LICENSE
Requires-Dist: async-generator (==1.10)
Requires-Dist: attrs (==22.1.0)
Requires-Dist: certifi (==2022.9.24)
Requires-Dist: cffi (==1.15.1)
Requires-Dist: charset-normalizer (==2.1.1)
Requires-Dist: colorama (==0.4.6)
Requires-Dist: colored (==1.4.4)
Requires-Dist: h11 (==0.14.0)
Requires-Dist: idna (==3.4)
Requires-Dist: outcome (==1.2.0)
Requires-Dist: packaging (==21.3)
Requires-Dist: pycparser (==2.21)
Requires-Dist: pyparsing (==3.0.9)
Requires-Dist: PySocks (==1.7.1)
Requires-Dist: python-dotenv (==0.21.0)
Requires-Dist: requests (==2.28.1)
Requires-Dist: selenium (==4.6.1)
Requires-Dist: sniffio (==1.3.0)
Requires-Dist: sortedcontainers (==2.4.0)
Requires-Dist: tqdm (==4.64.1)
Requires-Dist: trio (==0.22.0)
Requires-Dist: trio-websocket (==0.9.2)
Requires-Dist: urllib3 (==1.26.13)
Requires-Dist: webdriver-manager (==3.8.5)
Requires-Dist: wsproto (==1.2.0)
